Tarea3/tester.v
module TEST(
    input OINICIO, OCORTAR_PAN, OAGREGAR_LECHE, OAGREGAR_RESTO_DE_INGREDIENTES, 
                OREVOLVER, OHORNEAR, OBUDIN, OFRACASO,
    output reg clk, rst,
    output reg taza_leche, pan, leche_condensada,
    output reg barra_mantequilla, vainilla, taza_azucar, huevo
);

    // Generación del reloj
    always begin
        #5 clk = !clk;
    end

    // Vector de pruebas
    initial begin
        // Inicialización de señales
        clk = 0;
        rst = 1;
        taza_leche = 0;
        pan = 0;
        leche_condensada = 0;
        barra_mantequilla = 0;
        vainilla = 0;
        taza_azucar = 0;
        huevo = 0;

        // Caso 1: Receta exitosa
        #10 rst = 0;
        
        // Agregar pan
        pan = 1;
     
        
        // Agregar leche (1 taza)
        taza_leche = 1;
      
    
        
        // Agregar resto de ingredientes
        leche_condensada = 1;
        barra_mantequilla = 1;
        vainilla = 1;
        taza_azucar = 1;
        huevo = 1;
        
        
        
        // Desactivar señales
        #10 leche_condensada = 0;
        barra_mantequilla = 0;
        vainilla = 0;
        taza_azucar = 0;
        huevo = 0;
        taza_leche = 0;
        pan = 0;
        
        // Esperar proceso
        #200;

        // Caso 2: Fracaso por faltante de pan
        rst = 1;
        #10 rst = 0;
         // No pan
        #20 pan = 0;
     
        
        // Agregar leche (1 taza)
        taza_leche = 1;
      
    
        
        // Agregar resto de ingredientes
        leche_condensada = 1;
        barra_mantequilla = 1;
        vainilla = 1;
        taza_azucar = 1;
        huevo = 1;
        
        
        
        // Desactivar señales
        #10 leche_condensada = 0;
        barra_mantequilla = 0;
        vainilla = 0;
        taza_azucar = 0;
        huevo = 0;
        taza_leche = 0;
        pan = 0;
        
        // Esperar proceso
        #200
        $finish;
    end



endmodule

Tarea3/budin.v
module budin #(
    parameter   INICIO = 0, CORTAR_PAN = 1, AGREGAR_LECHE = 2, AGREGAR_RESTO_DE_INGREDIENTES = 3, 
                REVOLVER = 4, HORNEAR = 5, BUDIN = 6, FRACASO = 7
) (
    input clk, rst,
    input taza_leche, pan, leche_condensada,
    input barra_mantequilla,
    input vainilla,
    input taza_azucar,
    input huevo,
    output reg  OINICIO, OCORTAR_PAN, OAGREGAR_LECHE, OAGREGAR_RESTO_DE_INGREDIENTES, 
                OREVOLVER, OHORNEAR, OBUDIN, OFRACASO
);
reg [2:0] state, next_state;
reg [3:0] hornear_counter;
reg [2:0] counter;
reg ingredientes_completos;






always @(posedge clk) begin
    if (rst) begin
        state <= 0;
        next_state <= 0;
        counter <= 0;
        hornear_counter <= 0;
        // Reset todos los registros de ingredientes
       ingredientes_completos <= 0;
        OINICIO <= 0; OCORTAR_PAN <= 0; OAGREGAR_LECHE <= 0; 
        OAGREGAR_RESTO_DE_INGREDIENTES <= 0; OREVOLVER <= 0; 
        OHORNEAR <= 0; OBUDIN <= 0; OFRACASO <= 0;
    end else begin
        state <= next_state;
        
        // Contadores para timeout de cada estado
        case(state)
          
            AGREGAR_LECHE: begin
                if (counter < 2) begin
                    counter <= counter + 1;
                end 
            end
            HORNEAR: begin
                if (hornear_counter < 10)
                    hornear_counter <= hornear_counter + 1;
            end
        endcase
    end 
end

always @* begin
   if ( pan && taza_leche && leche_condensada && barra_mantequilla && vainilla &&  taza_azucar && huevo) begin
        ingredientes_completos = 1;  
   end else
    case (state)
        INICIO: begin
            OINICIO = 1;
            OCORTAR_PAN = 0;
            OAGREGAR_LECHE = 0;
            OAGREGAR_RESTO_DE_INGREDIENTES = 0;
            OREVOLVER = 0;
            OHORNEAR = 0;
            OBUDIN = 0;
            OFRACASO = 0;
            next_state = CORTAR_PAN;
        end
        
        CORTAR_PAN: begin
            OINICIO = 0;
            OCORTAR_PAN = 1;
            OAGREGAR_LECHE = 0;
            OAGREGAR_RESTO_DE_INGREDIENTES = 0;
            OREVOLVER = 0;
            OHORNEAR = 0;
            OBUDIN = 0;
            OFRACASO = 0;
            next_state = AGREGAR_LECHE;
            
        end
        
        AGREGAR_LECHE: begin
            OINICIO = 0;
            OCORTAR_PAN = 0;
            OAGREGAR_LECHE = 1;
            OAGREGAR_RESTO_DE_INGREDIENTES = 0;
            OREVOLVER = 0;
            OHORNEAR = 0;
            OBUDIN = 0;
            OFRACASO = 0; 
            if (counter >= 2) begin
                next_state = AGREGAR_RESTO_DE_INGREDIENTES;
            end else begin
                next_state = AGREGAR_LECHE;
            end
           
        end
        
        AGREGAR_RESTO_DE_INGREDIENTES: begin
            OINICIO = 0;
            OCORTAR_PAN = 0;
            OAGREGAR_LECHE = 0;
            OAGREGAR_RESTO_DE_INGREDIENTES = 1;
            OREVOLVER = 0;
            OHORNEAR = 0;
            OBUDIN = 0;
            OFRACASO = 0;
            next_state = REVOLVER;
          
        end
        
        REVOLVER: begin
            OINICIO = 0;
            OCORTAR_PAN = 0;
            OAGREGAR_LECHE = 0;
            OAGREGAR_RESTO_DE_INGREDIENTES = 0;
            OREVOLVER = 1;
            OHORNEAR = 0;
            OBUDIN = 0;
            OFRACASO = 0;
            next_state = HORNEAR;
        end
        HORNEAR: begin
            OINICIO = 0;
            OCORTAR_PAN = 0;
            OAGREGAR_LECHE = 0;
            OAGREGAR_RESTO_DE_INGREDIENTES = 0;
            OREVOLVER = 0;
            OHORNEAR = 1;
            OBUDIN = 0;
            OFRACASO = 0;
            if (hornear_counter >= 10) begin
                next_state = BUDIN;
            end else begin
                next_state = HORNEAR;
            end
        end
        
        BUDIN: begin
            OINICIO = 0;
            OCORTAR_PAN = 0;
            OAGREGAR_LECHE = 0;
            OAGREGAR_RESTO_DE_INGREDIENTES = 0;
            OREVOLVER = 0;
            OHORNEAR = 0;
            if (ingredientes_completos) begin
                OBUDIN = 1;
                next_state = BUDIN;
                
            end else begin
            OBUDIN = 0;
            OFRACASO = 0;
            next_state = FRACASO;
            end
        end
        
        FRACASO: begin
            OINICIO = 0;
            OCORTAR_PAN = 0;
            OAGREGAR_LECHE = 0;
            OAGREGAR_RESTO_DE_INGREDIENTES = 0;
            OREVOLVER = 0;
            OHORNEAR = 0;
            OBUDIN = 0;
            OFRACASO = 1;
            next_state = FRACASO;
        end
        
        default: begin
            OINICIO = 0;
            OCORTAR_PAN = 0;
            OAGREGAR_LECHE = 0;
            OAGREGAR_RESTO_DE_INGREDIENTES = 0;
            OREVOLVER = 0;
            OHORNEAR = 0;
            OBUDIN = 0;
            OFRACASO = 0;
            next_state = INICIO;
        end
    endcase
end
endmodule

Tarea3/testbench.v
`include "budin.v"
`include "tester.v"

module tb;

    budin dut(
        .clk(clk),
        .rst(rst),
        .taza_leche(taza_leche),
        .pan(pan),
        .leche_condensada(leche_condensada),
        .barra_mantequilla(barra_mantequilla),
        .vainilla(vainilla),
        .taza_azucar(taza_azucar),
        .huevo(huevo),
        .OINICIO(OINICIO),
        .OCORTAR_PAN(OORTAR_PAN),
        .OAGREGAR_LECHE(OAGREGAR_LECHE),
        .OAGREGAR_RESTO_DE_INGREDIENTES(OAGREGAR_RESTO_DE_INGREDIENTES),
        .OREVOLVER(OREVOLVER),
        .OHORNEAR(OHORNEAR),
        .OBUDIN(OBUDIN),
        .OFRACASO(OFRACASO)
    );

    TEST tester(
        .clk(clk),
        .rst(rst),
        .taza_leche(taza_leche),
        .pan(pan),
        .leche_condensada(leche_condensada),
        .barra_mantequilla(barra_mantequilla),
        .vainilla(vainilla),
        .taza_azucar(taza_azucar),
        .huevo(huevo),
        .OINICIO(OINICIO),
        .OCORTAR_PAN(OCORTAR_PAN),
        .OAGREGAR_LECHE(OAGREGAR_LECHE),
        .OAGREGAR_RESTO_DE_INGREDIENTES(OAGREGAR_RESTO_DE_INGREDIENTES),
        .OREVOLVER(OREVOLVER),
        .OHORNEAR(OHORNEAR),
        .OBUDIN(OBUDIN),
        .OFRACASO(OFRACASO)
    );

    initial begin
        $dumpfile("tb.vcd");
        $dumpvars;
    end

endmodule

Tarea3/tb.vcd
$date
	Sun Nov 17 19:50:01 2024
$end
$version
	Icarus Verilog
$end
$timescale
	1s
$end
$scope module tb $end
$var wire 1 ! OCORTAR_PAN $end
$var wire 1 " vainilla $end
$var wire 1 # taza_leche $end
$var wire 1 $ taza_azucar $end
$var wire 1 % rst $end
$var wire 1 & pan $end
$var wire 1 ' leche_condensada $end
$var wire 1 ( huevo $end
$var wire 1 ) clk $end
$var wire 1 * barra_mantequilla $end
$var wire 1 + OREVOLVER $end
$var wire 1 , OORTAR_PAN $end
$var wire 1 - OINICIO $end
$var wire 1 . OHORNEAR $end
$var wire 1 / OFRACASO $end
$var wire 1 0 OBUDIN $end
$var wire 1 1 OAGREGAR_RESTO_DE_INGREDIENTES $end
$var wire 1 2 OAGREGAR_LECHE $end
$scope module dut $end
$var wire 1 " vainilla $end
$var wire 1 # taza_leche $end
$var wire 1 $ taza_azucar $end
$var wire 1 % rst $end
$var wire 1 & pan $end
$var wire 1 ' leche_condensada $end
$var wire 1 ( huevo $end
$var wire 1 ) clk $end
$var wire 1 * barra_mantequilla $end
$var parameter 32 3 AGREGAR_LECHE $end
$var parameter 32 4 AGREGAR_RESTO_DE_INGREDIENTES $end
$var parameter 32 5 BUDIN $end
$var parameter 32 6 CORTAR_PAN $end
$var parameter 32 7 FRACASO $end
$var parameter 32 8 HORNEAR $end
$var parameter 32 9 INICIO $end
$var parameter 32 : REVOLVER $end
$var reg 1 2 OAGREGAR_LECHE $end
$var reg 1 1 OAGREGAR_RESTO_DE_INGREDIENTES $end
$var reg 1 0 OBUDIN $end
$var reg 1 , OCORTAR_PAN $end
$var reg 1 / OFRACASO $end
$var reg 1 . OHORNEAR $end
$var reg 1 - OINICIO $end
$var reg 1 + OREVOLVER $end
$var reg 3 ; counter [2:0] $end
$var reg 4 < hornear_counter [3:0] $end
$var reg 1 = ingredientes_completos $end
$var reg 3 > next_state [2:0] $end
$var reg 3 ? state [2:0] $end
$upscope $end
$scope module tester $end
$var wire 1 2 OAGREGAR_LECHE $end
$var wire 1 1 OAGREGAR_RESTO_DE_INGREDIENTES $end
$var wire 1 0 OBUDIN $end
$var wire 1 ! OCORTAR_PAN $end
$var wire 1 / OFRACASO $end
$var wire 1 . OHORNEAR $end
$var wire 1 - OINICIO $end
$var wire 1 + OREVOLVER $end
$var reg 1 * barra_mantequilla $end
$var reg 1 ) clk $end
$var reg 1 ( huevo $end
$var reg 1 ' leche_condensada $end
$var reg 1 & pan $end
$var reg 1 % rst $end
$var reg 1 $ taza_azucar $end
$var reg 1 # taza_leche $end
$var reg 1 " vainilla $end
$upscope $end
$upscope $end
$enddefinitions $end
$comment Show the parameter values. $end
$dumpall
b100 :
b0 9
b101 8
b111 7
b1 6
b110 5
b11 4
b10 3
$end
#0
$dumpvars
bx ?
b0 >
x=
bx <
bx ;
02
01
00
0/
0.
0-
0,
0+
0*
0)
0(
0'
0&
1%
0$
0#
0"
z!
$end
#5
b1 >
1-
0=
b0 <
b0 ;
b0 ?
1)
#10
1=
0)
1(
1$
1"
1*
1'
1#
1&
0%
#15
b1 ?
1)
#20
b10 >
1,
0-
0)
0&
0#
0(
0$
0"
0*
0'
#25
12
0,
b10 ?
1)
#30
0)
#35
b1 ;
1)
#40
0)
#45
b11 >
b10 ;
1)
#50
0)
#55
b100 >
11
02
b11 ?
1)
#60
0)
#65
b101 >
1+
01
b100 ?
1)
#70
0)
#75
1.
0+
b101 ?
1)
#80
0)
#85
b1 <
1)
#90
0)
#95
b10 <
1)
#100
0)
#105
b11 <
1)
#110
0)
#115
b100 <
1)
#120
0)
#125
b101 <
1)
#130
0)
#135
b110 <
1)
#140
0)
#145
b111 <
1)
#150
0)
#155
b1000 <
1)
#160
0)
#165
b1001 <
1)
#170
0)
#175
b110 >
b1010 <
1)
#180
0)
#185
10
0.
b110 ?
1)
#190
0)
#195
1)
#200
0)
#205
1)
#210
0)
#215
1)
#220
0)
1%
#225
1-
00
0=
b0 <
b0 ;
b1 >
b0 ?
1)
#230
0)
0%
#235
b10 >
1,
0-
b1 ?
1)
#240
0)
#245
12
0,
b10 ?
1)
#250
0)
1(
1$
1"
1*
1'
1#
#255
b1 ;
1)
#260
0)
0#
0(
0$
0"
0*
0'
#265
b11 >
b10 ;
1)
#270
0)
#275
b100 >
11
02
b11 ?
1)
#280
0)
#285
b101 >
1+
01
b100 ?
1)
#290
0)
#295
1.
0+
b101 ?
1)
#300
0)
#305
b1 <
1)
#310
0)
#315
b10 <
1)
#320
0)
#325
b11 <
1)
#330
0)
#335
b100 <
1)
#340
0)
#345
b101 <
1)
#350
0)
#355
b110 <
1)
#360
0)
#365
b111 <
1)
#370
0)
#375
b1000 <
1)
#380
0)
#385
b1001 <
1)
#390
0)
#395
b110 >
b1010 <
1)
#400
0)
#405
b111 >
0.
b110 ?
1)
#410
0)
#415
1/
b111 ?
1)
